puhu/__init__.py
puhu/_core.pypy310-pp73-aarch64-linux-gnu.so
puhu/enums.py
puhu/image.py
puhu/operations.py
puhu/tests/__init__.py
puhu/tests/test_enums.py
puhu/tests/test_image.py
puhu/tests/test_paste.py
puhu-0.3.0.dist-info/METADATA
puhu-0.3.0.dist-info/WHEEL
puhu-0.3.0.dist-info/licenses/LICENSE
puhu-0.3.0.dist-info/RECORD
