Metadata-Version: 2.4
Name: puhu
Version: 0.3.0
Classifier: Development Status :: 3 - Alpha
Classifier: Intended Audience :: Developers
Classifier: License :: OSI Approved :: MIT License
Classifier: Programming Language :: Python :: 3
Classifier: Programming Language :: Python :: 3.8
Classifier: Programming Language :: Python :: 3.9
Classifier: Programming Language :: Python :: 3.10
Classifier: Programming Language :: Python :: 3.11
Classifier: Programming Language :: Python :: 3.12
Classifier: Programming Language :: Rust
Classifier: Topic :: Multimedia :: Graphics
Classifier: Topic :: Software Development :: Libraries :: Python Modules
Requires-Dist: pytest>=7.0 ; extra == 'dev'
Requires-Dist: pytest-benchmark>=4.0 ; extra == 'dev'
Requires-Dist: numpy>=1.20 ; extra == 'dev'
Provides-Extra: dev
License-File: LICENSE
Summary: A modern, high-performance image processing library for Python, powered by Rust.
Keywords: image,processing,pillow,rust,performance
Author-email: Bilal Tonga <bilaltonga@gmail.com>
License: MIT
Requires-Python: >=3.8
Project-URL: Documentation, https://bgunebakan.github.io/puhu
Project-URL: Homepage, https://github.com/bgunebakan/puhu
Project-URL: Issues, https://github.com/bgunebakan/puhu/issues
Project-URL: Repository, https://github.com/bgunebakan/puhu
